terrapyn/__init__.py
terrapyn/bq/__init__.py
terrapyn/bq/data.py
terrapyn/bq/io.py
terrapyn_bq-0.1.0.dist-info/METADATA
terrapyn_bq-0.1.0.dist-info/WHEEL
terrapyn_bq-0.1.0.dist-info/licenses/LICENSE.md
terrapyn_bq-0.1.0.dist-info/RECORD
