Metadata-Version: 2.4
Name: terrapyn-bq
Version: 0.1.0
Summary: BigQuery module for terrapyn toolkit.
Author-email: Colin Hill <colinalastairhill@gmail.com>
License: BSD License
License-File: LICENSE.md
Classifier: Development Status :: 5 - Production/Stable
Classifier: Intended Audience :: Developers
Classifier: License :: OSI Approved :: BSD License
Classifier: Programming Language :: Python :: 3.10
Classifier: Programming Language :: Python :: 3.11
Classifier: Programming Language :: Python :: 3.12
Classifier: Programming Language :: Python :: 3.13
Requires-Python: >=3.10
Requires-Dist: google-cloud-bigquery>=3.36.0
Requires-Dist: pandas>=2.3.2
Requires-Dist: shapely>=2.1.1
Requires-Dist: terrapyn>=0.3.0
